{
  "lemma": "beijing",
  "count": 1,
  "pos_dist": {
    "PROPN": 1
  },
  "sentences": {
    "featured": [
      {
        "text": "The women’s softball team that won gold for Japan at the Beijing Olympics is reported to have used blood-type theories to customize training for each player.",
        "source": "2016_105_02-105學測英文科_定稿",
        "audio_file": "data/output/tts_audio/sentences/beijing_ex_0_f75f477b.mp3"
      }
    ],
    "other": []
  },
  "definition": {
    "zh_def": "北京，中國的首都，位於北方，是中國的政治、文化和教育中心。",
    "en_def": "Beijing, the capital of China, located in the north, is the political, cultural, and educational center of the country.",
    "example": "Beijing is known for its historical sites like the Great Wall and the Forbidden City."
  },
  "sentences_removed": 0
}