{
  "lemma": "budget",
  "count": 10,
  "pos_dist": {
    "NOUN": 9,
    "VERB": 1
  },
  "sentences": {
    "featured": [
      {
        "text": "After all, you must live within a limited budget.",
        "source": "2006_95_95english",
        "audio_file": "data/output/tts_audio/sentences/budget_ex_0_f6595310.mp3"
      },
      {
        "text": "The army had no budget to make the purchase.",
        "source": "2013_102_02-102學測英文(定稿) ",
        "audio_file": "data/output/tts_audio/sentences/budget_ex_1_c8c63e7e.mp3"
      },
      {
        "text": "The original budget for my round-island trip was NT$5,000, but the ______ cost is likely to be 50 percent higher.",
        "source": "2022_111_02-111學測英文試卷",
        "audio_file": "data/output/tts_audio/sentences/budget_ex_2_6b0eb0e8.mp3"
      },
      {
        "text": "To stick to a tight budget, Robert bought a more ______ LED TV instead of a fancy, expensive 3D TV.",
        "source": "2015_104_02-104學測英文定稿",
        "audio_file": "data/output/tts_audio/sentences/budget_ex_3_246fbe36.mp3"
      },
      {
        "text": "Today, they provide low-budget, overnight lodging in commerce centers in large cities worldwide.",
        "source": "2025_114_02-114學測英文試題",
        "audio_file": "data/output/tts_audio/sentences/budget_ex_4_6e1b0daa.mp3"
      }
    ],
    "other": [
      {
        "text": "While offering budget-conscious travelers a unique option, capsule hotels may not be suitable for everyone.",
        "source": "2025_114_02-114學測英文試題",
        "audio_file": ""
      },
      {
        "text": "But learning to budget your money is the first lesson you must learn to be independent.",
        "source": "2006_95_95english",
        "audio_file": ""
      },
      {
        "text": "The scientist’s project to build a modern laboratory was __________ on account of its huge budget.",
        "source": "2001_90_90學測_english",
        "audio_file": ""
      }
    ]
  },
  "definition": {
    "zh_def": "預算；計劃在特定時間內花費的金額。",
    "en_def": "A plan for managing income and expenses over a specific period.",
    "example": "We need to create a budget for our vacation to avoid overspending."
  },
  "sentences_removed": 2
}