{
  "lemma": "bulky",
  "count": 1,
  "pos_dist": {
    "ADJ": 1
  },
  "sentences": {
    "featured": [
      {
        "text": "Most people feel disgusted at the sight of these bulky, slow-moving creatures.",
        "source": "2010_99_02-99學測英文試卷定稿",
        "audio_file": "data/output/tts_audio/sentences/bulky_ex_0_3728afcd.mp3"
      }
    ],
    "other": []
  },
  "definition": {
    "zh_def": "體積大且笨重的",
    "en_def": "Large and difficult to carry or handle due to size or weight.",
    "example": "The bulky package was hard to fit into the car."
  },
  "sentences_removed": 0
}