{
  "lemma": "endanger",
  "count": 7,
  "pos_dist": {
    "VERB": 7
  },
  "sentences": {
    "featured": [
      {
        "text": "D. Daniel To me, a zoo can be a good place for endangered species which have difficulty finding suitable mates in the wild.",
        "source": "2025_114_02-114學測英文試題",
        "audio_file": "data/output/tts_audio/sentences/endanger_ex_0_41eee2c0.mp3"
      },
      {
        "text": "Your health might thus be endangered.",
        "source": "2019_108_01-108學測英文試卷定稿",
        "audio_file": "data/output/tts_audio/sentences/endanger_ex_1_0e555735.mp3"
      },
      {
        "text": "In the Indian state of Assam, growing numbers of tea farms are destroying the Asian elephant’s habitats and endangering their population.",
        "source": "2023_112_02-112學測英文試卷",
        "audio_file": "data/output/tts_audio/sentences/endanger_ex_2_348c4c35.mp3"
      }
    ],
    "other": [
      {
        "text": "Even if an animal is endangered, does that justify restricting its freedom?",
        "source": "2025_114_02-114學測英文試題",
        "audio_file": ""
      },
      {
        "text": "Most people probably don’t feel sympathy for these endangered creatures, but they do need protecting.",
        "source": "2010_99_02-99學測英文試卷定稿",
        "audio_file": ""
      },
      {
        "text": "H. Henry Most animals in zoos are not endangered, nor are they being prepared for release into natural habitats.",
        "source": "2025_114_02-114學測英文試題",
        "audio_file": ""
      }
    ]
  },
  "definition": {
    "zh_def": "使處於危險之中",
    "en_def": "To put someone or something at risk of harm or danger.",
    "example": "Pollution can endanger the health of marine life."
  },
  "sentences_removed": 1
}