{
  "lemma": "excite",
  "count": 1,
  "pos_dist": {
    "VERB": 1
  },
  "sentences": {
    "featured": [
      {
        "text": "How did Deborah feel when she first hurt her knee? (A) Excited. (B) Confused. (C) Ashamed.",
        "source": "2011_100_02-100學測英文試卷定稿",
        "audio_file": "data/output/tts_audio/sentences/excite_ex_0_354e4a10.mp3"
      }
    ],
    "other": []
  },
  "definition": {
    "zh_def": "使興奮；使激動",
    "en_def": "To cause strong feelings of enthusiasm and eagerness.",
    "example": "The news of the concert excited everyone in the crowd."
  },
  "sentences_removed": 0
}