{
  "lemma": "gain",
  "count": 14,
  "pos_dist": {
    "VERB": 13,
    "NOUN": 1
  },
  "sentences": {
    "featured": [
      {
        "text": "This centuries-old Chinese mind-body exercise is now gaining popularity in the United States.",
        "source": "2015_104_02-104學測英文定稿",
        "audio_file": "data/output/tts_audio/sentences/gain_ex_0_14c9c502.mp3"
      },
      {
        "text": "According to the author, what is the common view of those who have lost some weight first and gained it back later?",
        "source": "2005_94_94english",
        "audio_file": "data/output/tts_audio/sentences/gain_ex_1_bc259c02.mp3"
      },
      {
        "text": "In this way, these secret shoppers may help a business gain a competitive edge.",
        "source": "2024_113_02-113學測英文科定稿",
        "audio_file": "data/output/tts_audio/sentences/gain_ex_2_f44cb680.mp3"
      },
      {
        "text": "Marian Anderson (1897-1993) was an African American woman who gained fame as a concert singer in this climate of racism.",
        "source": "2002_91_91學測_english",
        "audio_file": "data/output/tts_audio/sentences/gain_ex_3_e97b9dfc.mp3"
      },
      {
        "text": "By reading and listening to folk tales, we may gain a better understanding of the true values, beliefs, and goals of a people. 41.",
        "source": "2002_91_91學測補考_english",
        "audio_file": "data/output/tts_audio/sentences/gain_ex_4_4e03a824.mp3"
      }
    ],
    "other": [
      {
        "text": "But trading online is gaining popularity these days, with several sites in bills operation, including HomeExchanges.",
        "source": "2010_99_02-99學測英文試卷定稿",
        "audio_file": ""
      },
      {
        "text": "But we often gain back what we have lost.",
        "source": "2005_94_94english",
        "audio_file": ""
      },
      {
        "text": "It can be inferred from the passage that Howard will probably gain his weight back again.",
        "source": "2000_89_89年學測英文科",
        "audio_file": ""
      },
      {
        "text": "Benson married Julie soon after he had _____ her heart and gained her parents’ approval.",
        "source": "2016_105_02-105學測英文科_定稿",
        "audio_file": ""
      },
      {
        "text": "The “no pain, no gain” view of exercise is now considered old-fashioned.",
        "source": "2021_110_110學測英文試卷 ",
        "audio_file": ""
      },
      {
        "text": "To gain more ______, some legislators would get into violent physical fights so that they may appear in TV news reports.",
        "source": "2005_94_94english",
        "audio_file": ""
      },
      {
        "text": "From Turkey, she boarded gained strength in body and mind.",
        "source": "2022_111_02-111學測英文試卷",
        "audio_file": ""
      },
      {
        "text": "The hula hoop gained international popularity in the late 1950s, when a plastic version was successfully marketed by California’s Wham-O toy company.",
        "source": "2023_112_02-112學測英文試卷",
        "audio_file": ""
      }
    ]
  },
  "definition": {
    "zh_def": "獲得或增加某物，尤其是利益或好處。",
    "en_def": "To obtain or increase something, especially a benefit or advantage.",
    "example": "She worked hard to gain the trust of her colleagues."
  },
  "sentences_removed": 1
}