{
  "lemma": "greenburger",
  "count": 5,
  "pos_dist": {
    "PROPN": 5
  },
  "sentences": {
    "featured": [
      {
        "text": "From (A) to (H) in the above chatroom discussions, which ones show that GreenBurger can be a choice for the chatroom participants themselves only under certain circumstances?",
        "source": "2023_112_02-112學測英文試卷",
        "audio_file": "data/output/tts_audio/sentences/greenburger_ex_0_32924a67.mp3"
      },
      {
        "text": "Especially when a burger craving hits…a GreenBurger does the trick.",
        "source": "2023_112_02-112學測英文試卷",
        "audio_file": "data/output/tts_audio/sentences/greenburger_ex_1_8a26d26d.mp3"
      },
      {
        "text": "We’ve been mostly vegan 90% of the time for the last 6 years and we cannot thank GreenBurger enough!",
        "source": "2023_112_02-112學測英文試卷",
        "audio_file": "data/output/tts_audio/sentences/greenburger_ex_2_2775f804.mp3"
      },
      {
        "text": "Read the following chatroom discussions about GreenBurger, a product using alternative-meat patties.",
        "source": "2023_112_02-112學測英文試卷",
        "audio_file": "data/output/tts_audio/sentences/greenburger_ex_3_cfaaf207.mp3"
      }
    ],
    "other": []
  },
  "definition": {
    "zh_def": "綠色漢堡，通常指使用植物性成分製作的漢堡，旨在提供健康或環保的飲食選擇。",
    "en_def": "A greenburger is a burger made primarily from plant-based ingredients, aimed at providing a healthier or more environmentally friendly food option.",
    "example": "I ordered a greenburger for lunch because I wanted a healthier meal."
  },
  "sentences_removed": 1
}