{
  "lemma": "increase",
  "count": 36,
  "pos_dist": {
    "VERB": 29,
    "NOUN": 7
  },
  "sentences": {
    "featured": [
      {
        "text": "The number of athletes 28 in the Summer Paralympic Games has increased from 400 athletes from 23 countries in 1960 to 3,806 athletes from 136 countries in 2004.",
        "source": "2009_98_02-98學測英文試題定稿",
        "audio_file": "data/output/tts_audio/sentences/increase_ex_0_851d8972.mp3"
      },
      {
        "text": "Another way to increase creativity is to take risks.",
        "source": "2018_107_02-107學測英文試卷定稿",
        "audio_file": "data/output/tts_audio/sentences/increase_ex_1_f62c8bb8.mp3"
      },
      {
        "text": "The memory _____ of the new computer has been increased so that more information can be stored.",
        "source": "2012_101_02-101學測英文試卷定稿",
        "audio_file": "data/output/tts_audio/sentences/increase_ex_2_92c37eb6.mp3"
      },
      {
        "text": "Now that we all use pencils, doodling is on the increase, and the quality of pencilwomanship is impressive, as you can tell from my handwriting in this letter.",
        "source": "2009_98_02-98學測英文試題定稿",
        "audio_file": "data/output/tts_audio/sentences/increase_ex_3_c599a2e7.mp3"
      },
      {
        "text": "An extremely mild winter allowed more mosquitoes than usual to survive, while the unusually high temperatures in that scorching summer further increased their number by speeding up their life cycle.",
        "source": "2018_107_02-107學測英文試卷定稿",
        "audio_file": "data/output/tts_audio/sentences/increase_ex_4_6d136cce.mp3"
      }
    ],
    "other": [
      {
        "text": "Which of the following statements is true regarding GABA in zebrafish? (A) Increasing GABA level facilitates neuron activities.",
        "source": "2022_111_02-111學測英文試卷",
        "audio_file": ""
      },
      {
        "text": "Small amounts of regular activity, even just standing and moving around, throughout the day is enough to bring the increased levels back down.",
        "source": "2015_104_02-104學測英文定稿",
        "audio_file": ""
      },
      {
        "text": "With multiple queens at work, its population increases rapidly.",
        "source": "2005_94_94english",
        "audio_file": ""
      },
      {
        "text": "The robot described itself as an extension of a person to help humans increase the workload.",
        "source": "1998_87_87年學測英文科",
        "audio_file": ""
      },
      {
        "text": "All the time that we spend rooted in the chair is linked to increased risks of so many deadly diseases that experts have named this modern-day health epidemic the “sitting disease.”",
        "source": "2015_104_02-104學測英文定稿",
        "audio_file": ""
      },
      {
        "text": "Iceland has increased their fish catch by 30% in the last 20 years.",
        "source": "2024_113_02-113學測英文科定稿",
        "audio_file": ""
      },
      {
        "text": "The problem is 18 when airplanes fly at higher altitudes, where the difference between the inside and outside pressure increases, causing added stress.",
        "source": "2022_111_02-111學測英文試卷",
        "audio_file": ""
      },
      {
        "text": "With rising oil prices, there is an increasing _____ for people to ride bicycles to work.",
        "source": "2009_98_02-98學測英文試題定稿",
        "audio_file": ""
      },
      {
        "text": "The present design of the oversized automobile is largely responsible not only for increasing death toll on the highways but also for the rapid depletion of our resources of petroleum, for the pollution of our environment, and for the congestion and inconvenience of our cities.",
        "source": "1995_84_84年學測英文科",
        "audio_file": ""
      },
      {
        "text": "Between the 12th and 15th centuries, trade increased between Arabia, Persia, and Zanzibar, bringing the archipelago both wealth and power.",
        "source": "2023_112_02-112學測英文試卷",
        "audio_file": ""
      },
      {
        "text": "They have had a great increase in population since 2001.",
        "source": "2009_98_02-98學測英文試題定稿",
        "audio_file": ""
      },
      {
        "text": "Such demand increased with the rise of western movies, and many cowboys with masterful skills on horseback found a new 27 as a stunt person.",
        "source": "2022_111_02-111學測英文試卷",
        "audio_file": ""
      },
      {
        "text": "The increasing population in Texas raised the risk of contracting the disease.",
        "source": "2018_107_02-107學測英文試卷定稿",
        "audio_file": ""
      },
      {
        "text": "For example, girls are born with more sensitive hearing than boys, and the difference increases as kids grow up.",
        "source": "2007_96_02-96",
        "audio_file": ""
      },
      {
        "text": "Psychologically, this exercise may increase communication between the body and the mind and enable one to deal with other people more effectively.",
        "source": "2015_104_02-104學測英文定稿",
        "audio_file": ""
      },
      {
        "text": "Following increasing calls for the return of artistic objects that were removed decades or centuries ago, some of the world’s leading museums have signed a declaration that they will not hand back the ancient artifacts to their countries of origin.",
        "source": "2004_93_93english",
        "audio_file": ""
      },
      {
        "text": "While some say free online courses are a great way to increase the enrollment of minority students, others have said they will leave many students behind.",
        "source": "2014_103_02-103學測英文-定稿",
        "audio_file": ""
      },
      {
        "text": "These increases put great stress on the islands’ resources and environment.",
        "source": "2009_98_02-98學測英文試題定稿",
        "audio_file": ""
      },
      {
        "text": "Laughter, too, has a beneficial effect on our immune system, (38) the production of white blood cells and increasing our resistance to infection.(39) makes a difference to our appearance, too, when we relax our facial muscles!",
        "source": "1998_87_87年學測英文科",
        "audio_file": ""
      },
      {
        "text": "Founded in 1992, with some 28,000 listings, this company itself as the world’s largest home exchange club, reporting that membership has increased 30% this year.",
        "source": "2010_99_02-99學測英文試卷定稿",
        "audio_file": ""
      },
      {
        "text": "As India’s size decreases, the thickness of the Himalayas increases.",
        "source": "2007_96_02-96",
        "audio_file": ""
      },
      {
        "text": "Mistrust increases and rejection and repression surface.",
        "source": "2005_94_94english",
        "audio_file": ""
      },
      {
        "text": "This means that no increased competition arises for the water or land presently used for food production.",
        "source": "2021_110_110學測英文試卷 ",
        "audio_file": ""
      },
      {
        "text": "According to this passage, the American households using digital cameras will increase if __________.",
        "source": "2002_91_91學測補考_english",
        "audio_file": ""
      },
      {
        "text": "By exhaling air from the lungs in short (36) of laughter, breathing is quickened and heartbeats increased, which achieves (37) good as ten minutes on an exercise bike.",
        "source": "1998_87_87年學測英文科",
        "audio_file": ""
      },
      {
        "text": "But without that activity, blood sugar levels and blood pressure keep creeping up, steadily damaging the inside of the arteries and increasing the risk of diabetes, heart disease, stroke, and other serious diseases.",
        "source": "2015_104_02-104學測英文定稿",
        "audio_file": ""
      },
      {
        "text": "The increasing population in Saudi Arabia has resulted in shortages of fresh water.",
        "source": "2018_107_02-107學測英文試卷定稿",
        "audio_file": ""
      },
      {
        "text": "Gaps in the treetops resulting from crown shyness may allow trees to increase their 14 light and enhance photosynthesis.",
        "source": "2023_112_02-112學測英文試卷",
        "audio_file": ""
      }
    ]
  },
  "definition": {
    "zh_def": "增加；提高",
    "en_def": "To become larger or greater in size, amount, or degree.",
    "example": "The company plans to increase its production next year."
  },
  "sentences_removed": 3
}