{
  "lemma": "infant",
  "count": 4,
  "pos_dist": {
    "NOUN": 4
  },
  "sentences": {
    "featured": [
      {
        "text": "In fact, the infant is the most vulnerable member of society to this chemical.",
        "source": "2003_92_92學測補考_english",
        "audio_file": "data/output/tts_audio/sentences/infant_ex_0_a743c0a3.mp3"
      },
      {
        "text": "As of 1997, the orphanage, which depends on private contributions, has saved more than 100 infants.",
        "source": "2001_90_90學測_english",
        "audio_file": "data/output/tts_audio/sentences/infant_ex_1_fddc4326.mp3"
      },
      {
        "text": "The mother’s fear of loss especially makes sense since the infant/toddler years of life are fragile ones.",
        "source": "2018_107_02-107學測英文試卷定稿",
        "audio_file": "data/output/tts_audio/sentences/infant_ex_2_ba947bec.mp3"
      }
    ],
    "other": []
  },
  "definition": {
    "zh_def": "嬰兒；剛出生不久的幼兒。",
    "en_def": "A very young child, especially one that is just born or not yet walking.",
    "example": "The infant slept peacefully in her crib."
  },
  "sentences_removed": 1
}