{
  "lemma": "instal",
  "count": 5,
  "pos_dist": {
    "VERB": 5
  },
  "sentences": {
    "featured": [
      {
        "text": "Knight’s traffic signal was installed near London’s Westminster Bridge in December 1868, but the system was short-lived.",
        "source": "2025_114_02-114學測英文試題",
        "audio_file": "data/output/tts_audio/sentences/instal_ex_0_511e9fb2.mp3"
      },
      {
        "text": "Installed in Detroit in 1920, Potts’ three-color system allowed for the added signal “proceed with caution” to be displayed.",
        "source": "2025_114_02-114學測英文試題",
        "audio_file": "data/output/tts_audio/sentences/instal_ex_1_62222522.mp3"
      },
      {
        "text": "Picking up on teens' interest in computer games, Hilfiger sponsored a Nintendo competition and installed Nintendo terminals in his stores.",
        "source": "2003_92_92學測_english",
        "audio_file": "data/output/tts_audio/sentences/instal_ex_2_7757c056.mp3"
      },
      {
        "text": "A laser clock would be installed on top of the Arc de Triomphe at the top of the Champs Elysees and three laser beams would pick out the hands showing the hours, minutes and seconds in the millennium countdown, Tiberi said.",
        "source": "1998_87_87年學測英文科",
        "audio_file": "data/output/tts_audio/sentences/instal_ex_3_c07b991e.mp3"
      }
    ],
    "other": []
  },
  "definition": {
    "zh_def": "安裝，將軟體或設備放置在可使用的狀態。",
    "en_def": "To set up software or equipment for use.",
    "example": "I need to install the new software on my computer."
  },
  "sentences_removed": 1
}