{
  "lemma": "line",
  "count": 20,
  "pos_dist": {
    "NOUN": 17,
    "VERB": 3
  },
  "sentences": {
    "featured": [
      {
        "text": "What does “a new chapter” in line 2, paragraph 1 mean? (A) A new unit of a book.",
        "source": "2007_96_02-96",
        "audio_file": "data/output/tts_audio/sentences/line_ex_0_11a9c7f2.mp3"
      },
      {
        "text": "Continuous as the stars that shine And twinkle on the Milky Way, They stretched in never-ending line Along the margin of a bay:",
        "source": "2000_89_89年學測英文科",
        "audio_file": "data/output/tts_audio/sentences/line_ex_1_e56bf8b9.mp3"
      },
      {
        "text": "We have to think of the bottom line.",
        "source": "2009_98_02-98學測英文試題定稿",
        "audio_file": "data/output/tts_audio/sentences/line_ex_2_9997e8df.mp3"
      },
      {
        "text": "“It’s a really hard thing to determine when they’ve crossed the line,” Mr. Power said.",
        "source": "2015_104_02-104學測英文定稿",
        "audio_file": "data/output/tts_audio/sentences/line_ex_3_374f4bfa.mp3"
      },
      {
        "text": "In line with the worldwide green movement, carmakers have been working hard to make their new models more _____ friendly to reduce pollution.",
        "source": "2016_105_02-105學測英文科_定稿",
        "audio_file": "data/output/tts_audio/sentences/line_ex_4_e03c89de.mp3"
      }
    ],
    "other": [
      {
        "text": "To line up in the laboratory.",
        "source": "2013_102_02-102學測英文(定稿) ",
        "audio_file": ""
      },
      {
        "text": "Public dwellings lined its ground level; a marketplace and two mosques also fit comfortably inside.",
        "source": "2005_94_94english",
        "audio_file": ""
      },
      {
        "text": "My mom is on the line.",
        "source": "1995_84_84年學測英文科",
        "audio_file": ""
      },
      {
        "text": "Thus they reach the 39 line together.",
        "source": "2009_98_02-98學測英文試題定稿",
        "audio_file": ""
      },
      {
        "text": "In this line of work, the person is paid to do daring actions that are deemed too 21 for the regular actor to perform, including jumping from heights, crashing cars, or fighting with weapons.",
        "source": "2022_111_02-111學測英文試卷",
        "audio_file": ""
      },
      {
        "text": "One of the first European books to be printed in movable type was Johannes Gutenberg's 42-line Bible.",
        "source": "1994_83_83年學測英文科",
        "audio_file": ""
      },
      {
        "text": "Deer are attracted to railway lines because of a need for iron in their diets.",
        "source": "2020_109_02-109學測英文試卷-定稿",
        "audio_file": ""
      },
      {
        "text": "The booth he built 25 only an old dial phone with a disconnected phone line.",
        "source": "2024_113_02-113學測英文科定稿",
        "audio_file": ""
      },
      {
        "text": "But many others enjoy a good fear spectacle, and line up to see the latest scary movie.",
        "source": "2025_114_02-114學測英文試題",
        "audio_file": ""
      },
      {
        "text": "What does it in the last line refer to? (A) Dioxin.",
        "source": "2003_92_92學測補考_english",
        "audio_file": ""
      },
      {
        "text": "The sandals have subsequently undergone redesign, often appearing in bright colors in line with Californian beach culture.",
        "source": "2020_109_02-109學測英文試卷-定稿",
        "audio_file": ""
      },
      {
        "text": "Sasaki stated in an interview: “Because my thoughts couldn’t be 26 through a regular phone line, I wanted them to be carried on the wind.”",
        "source": "2024_113_02-113學測英文科定稿",
        "audio_file": ""
      },
      {
        "text": "Some kindergartens have adopted teaching methods along blood group lines, and even major companies reportedly make decisions about assignments based on an employee’s blood type.",
        "source": "2016_105_02-105學測英文科_定稿",
        "audio_file": ""
      },
      {
        "text": "The power workers had to work _____ to repair the power lines since the whole city was in the dark.",
        "source": "2003_92_92學測_english",
        "audio_file": ""
      }
    ]
  },
  "definition": {
    "zh_def": "一條長而窄的物體或一系列連續的點或標記。",
    "en_def": "A long, narrow mark or band; a series of points or marks that connect.",
    "example": "She drew a straight line on the paper."
  },
  "sentences_removed": 1
}