{
  "lemma": "longwang",
  "count": 2,
  "pos_dist": {
    "PROPN": 2
  },
  "sentences": {
    "featured": [
      {
        "text": "Korea and Japan 37 animal names and China likes names of gods such as Longwang (dragon king) and Fengshen (god of the wind).",
        "source": "2012_101_02-101學測英文試卷定稿",
        "audio_file": "data/output/tts_audio/sentences/longwang_ex_0_bbef5b1d.mp3"
      },
      {
        "text": "For example, the names of Nabi by South Korea, and Longwang by China were 40 with other names in 2007.",
        "source": "2012_101_02-101學測英文試卷定稿",
        "audio_file": "data/output/tts_audio/sentences/longwang_ex_1_d83e6b49.mp3"
      }
    ],
    "other": []
  },
  "definition": {
    "zh_def": "中國神話中的龍王，掌管水域和雨水的神祇。",
    "en_def": "In Chinese mythology, the Dragon King, a deity who governs bodies of water and rain.",
    "example": "The villagers prayed to the Longwang for rain during the drought."
  },
  "sentences_removed": 0
}