{
  "lemma": "loose",
  "count": 1,
  "pos_dist": {
    "ADJ": 1
  },
  "sentences": {
    "featured": [
      {
        "text": "A properly made kilt should not be so loose that the wearer can easily twist the kilt around the body, nor should it be so tight that it causes bulging of the fabric where it is buckled.",
        "source": "2012_101_02-101學測英文試卷定稿",
        "audio_file": "data/output/tts_audio/sentences/loose_ex_0_04227f50.mp3"
      }
    ],
    "other": []
  },
  "definition": {
    "zh_def": "鬆的；不緊的；不牢固的",
    "en_def": "Not firmly held in place; not tight.",
    "example": "The screw was loose, causing the door to squeak."
  },
  "sentences_removed": 0
}