{
  "lemma": "maxsine",
  "count": 1,
  "pos_dist": {
    "PROPN": 1
  },
  "sentences": {
    "featured": [
      {
        "text": "Medvedev Vladimir, 43, and his son, Maxsine, 14, sailed from an unnamed eastern Russian seaport on August 18, to begin an ambitious around-the-world cruise.",
        "source": "1997_86_86年學測英文科",
        "audio_file": "data/output/tts_audio/sentences/maxsine_ex_0_cd2beacd.mp3"
      }
    ],
    "other": []
  },
  "definition": {
    "zh_def": "最大正弦值，通常用於數學和工程領域。",
    "en_def": "The maximum value of the sine function, often used in mathematics and engineering.",
    "example": "The maxsine of the angle is crucial for calculating the wave's amplitude."
  },
  "sentences_removed": 0
}