{
  "lemma": "meal",
  "count": 13,
  "pos_dist": {
    "NOUN": 13
  },
  "sentences": {
    "featured": [
      {
        "text": "But no matter what a child eats, brushing after each meal is still the best way to fight cavities.",
        "source": "2007_96_02-96",
        "audio_file": "data/output/tts_audio/sentences/meal_ex_0_bde884d4.mp3"
      },
      {
        "text": "In this course, you will learn __(22)__ to cook two weeks of healthy, inexpensive meals in just one day.",
        "source": "2003_92_92學測補考_english",
        "audio_file": "data/output/tts_audio/sentences/meal_ex_1_13f62284.mp3"
      },
      {
        "text": "But studies suggest that involving children in meal preparation is an important first step in getting them to try new foods.",
        "source": "2009_98_02-98學測英文試題定稿",
        "audio_file": "data/output/tts_audio/sentences/meal_ex_2_467795d0.mp3"
      },
      {
        "text": "Although he is a chef, Roberto _____ cooks his own meals.",
        "source": "2005_94_94english",
        "audio_file": "data/output/tts_audio/sentences/meal_ex_3_cfe497fc.mp3"
      },
      {
        "text": "Before long, a small meal at the end of the afternoon, involving tea and sandwiches, had become part of the British way of life.",
        "source": "2017_106_02-106學測英文試卷定稿",
        "audio_file": "data/output/tts_audio/sentences/meal_ex_4_c8517da1.mp3"
      }
    ],
    "other": [
      {
        "text": "To teach children about the meal preparation process.",
        "source": "2009_98_02-98學測英文試題定稿",
        "audio_file": ""
      },
      {
        "text": "At the end of the class, you __(25)__ with you classmates the meals you have created, and you will leave with recipe handouts and , more importantly, the ability to cook two weeks of fantastic, low-cost meals.",
        "source": "2003_92_92學測補考_english",
        "audio_file": ""
      },
      {
        "text": "This meal has become known as “high tea.”",
        "source": "2017_106_02-106學測英文試卷定稿",
        "audio_file": ""
      },
      {
        "text": "Eating dessert before meals may kill your ________.",
        "source": "2002_91_91學測補考_english",
        "audio_file": ""
      },
      {
        "text": "Which of the following groups will eat more balanced meals?",
        "source": "2009_98_02-98學測英文試題定稿",
        "audio_file": ""
      },
      {
        "text": "In working-class households, it was served with the main meal of the day, eaten when workers returned home after a day’s labor.",
        "source": "2017_106_02-106學測英文試卷定稿",
        "audio_file": ""
      }
    ]
  },
  "definition": {
    "zh_def": "一餐，通常指一天中吃的食物，可能包括早餐、午餐或晚餐。",
    "en_def": "A meal is food that is eaten at a specific time, typically consisting of multiple courses.",
    "example": "I usually have a big meal with my family on Sundays."
  },
  "sentences_removed": 1
}