{
  "lemma": "moran",
  "count": 11,
  "pos_dist": {
    "PROPN": 11
  },
  "sentences": {
    "featured": [
      {
        "text": "Moran came to the United States at age 7 with his family and settled in Philadelphia.",
        "source": "2024_113_02-113學測英文科定稿",
        "audio_file": "data/output/tts_audio/sentences/moran_ex_0_7e833d5b.mp3"
      },
      {
        "text": "In 1871 Moran joined the first US government survey of the Yellowstone region with photographer William Henry Jackson.",
        "source": "2024_113_02-113學測英文科定稿",
        "audio_file": "data/output/tts_audio/sentences/moran_ex_1_64d2afb6.mp3"
      },
      {
        "text": "It was the only national park established because of Moran’s works.",
        "source": "2024_113_02-113學測英文科定稿",
        "audio_file": "data/output/tts_audio/sentences/moran_ex_2_1867e0c7.mp3"
      },
      {
        "text": "Moran began painting by age 15, inspired by the landscape paintings of the British master J.M.W. Turner.",
        "source": "2024_113_02-113學測英文科定稿",
        "audio_file": "data/output/tts_audio/sentences/moran_ex_3_7e647dc2.mp3"
      }
    ],
    "other": [
      {
        "text": "Before Moran arrived, Yellowstone in the popular imagination was a harsh, wild place with hot water and steam coming out of hellish holes in the ground.",
        "source": "2024_113_02-113學測英文科定稿",
        "audio_file": ""
      },
      {
        "text": "Why does the author use “the blackened heart” in paragraph 2 to describe Moran’s hometown?",
        "source": "2024_113_02-113學測英文科定稿",
        "audio_file": ""
      },
      {
        "text": "Moran’s watercolors—the first color renderings of the area—as well as Jackson’s photos and the survey results were presented to the Congress.",
        "source": "2024_113_02-113學測英文科定稿",
        "audio_file": ""
      },
      {
        "text": "Showing great talent in painting, Moran was soon hired as an illustrator at Scribner’s Monthly, and later appointed chief illustrator by age 34.",
        "source": "2024_113_02-113學測英文科定稿",
        "audio_file": ""
      },
      {
        "text": "Captivated by the utterly fantastic sights Langford described, Moran became eager to see this odd territory for himself.",
        "source": "2024_113_02-113學測英文科定稿",
        "audio_file": ""
      },
      {
        "text": "That was all the nature that Moran knew.",
        "source": "2024_113_02-113學測英文科定稿",
        "audio_file": ""
      },
      {
        "text": "By the time Moran died, he had painted a dozen other areas that would become national parks or monuments.",
        "source": "2024_113_02-113學測英文科定稿",
        "audio_file": ""
      }
    ]
  },
  "definition": {
    "zh_def": "一種用於形容愚蠢或無知的人的貶義詞。",
    "en_def": "A derogatory term used to describe a person who is perceived as foolish or ignorant.",
    "example": "He acted like a moran when he ignored all the warnings."
  },
  "sentences_removed": 0
}