{
  "lemma": "movable",
  "count": 7,
  "pos_dist": {
    "ADJ": 7
  },
  "sentences": {
    "featured": [
      {
        "text": "One of the first European books to be printed in movable type was Johannes Gutenberg's 42-line Bible.",
        "source": "1994_83_83年學測英文科",
        "audio_file": "data/output/tts_audio/sentences/movable_ex_0_3b6d9bf4.mp3"
      },
      {
        "text": "Systems using movable arms were popular in Chicago, while those using the red and green lights were adopted in San Francisco.",
        "source": "2025_114_02-114學測英文試題",
        "audio_file": "data/output/tts_audio/sentences/movable_ex_1_94d26a1f.mp3"
      },
      {
        "text": "The use of movable type was first introduced by (A) William Caxton.",
        "source": "1994_83_83年學測英文科",
        "audio_file": "data/output/tts_audio/sentences/movable_ex_2_30f8080c.mp3"
      }
    ],
    "other": [
      {
        "text": "The first English book printed in movable type was (A) done from wood blocks one letter at a time.",
        "source": "1994_83_83年學測英文科",
        "audio_file": ""
      },
      {
        "text": "According to the passage, the use of movable type was considered as a \"great step forward\" because (A) it did not need a lot of wood.",
        "source": "1994_83_83年學測英文科",
        "audio_file": ""
      },
      {
        "text": "A great step forward was the use of movable type.",
        "source": "1994_83_83年學測英文科",
        "audio_file": ""
      },
      {
        "text": "Thus, he proposed a signaling system based on the railway movable-arm signal:",
        "source": "2025_114_02-114學測英文試題",
        "audio_file": ""
      }
    ]
  },
  "definition": {
    "zh_def": "可移動的，能夠被移動或改變位置的。",
    "en_def": "Able to be moved from one place to another.",
    "example": "The furniture in the room is movable, making it easy to rearrange."
  },
  "sentences_removed": 0
}