{
  "lemma": "murderer",
  "count": 1,
  "pos_dist": {
    "NOUN": 1
  },
  "sentences": {
    "featured": [
      {
        "text": "They’re thieves and murderers, all of them.”",
        "source": "2014_103_02-103學測英文-定稿",
        "audio_file": "data/output/tts_audio/sentences/murderer_ex_0_011a6121.mp3"
      }
    ],
    "other": []
  },
  "definition": {
    "zh_def": "謀殺者；故意殺人者",
    "en_def": "A person who unlawfully kills another person with intent.",
    "example": "The police arrested the murderer after a lengthy investigation."
  },
  "sentences_removed": 0
}