{
  "lemma": "narrate",
  "count": 1,
  "pos_dist": {
    "VERB": 1
  },
  "sentences": {
    "featured": [
      {
        "text": "Familiar fables can be narrated differently or extended in interesting and humorous ways.",
        "source": "2009_98_02-98學測英文試題定稿",
        "audio_file": "data/output/tts_audio/sentences/narrate_ex_0_2fa16b64.mp3"
      }
    ],
    "other": []
  },
  "definition": {
    "zh_def": "敘述；講述某事的過程或故事。",
    "en_def": "To tell a story or describe events in detail.",
    "example": "She decided to narrate her adventures during the summer vacation."
  },
  "sentences_removed": 0
}