{
  "lemma": "sake",
  "count": 1,
  "pos_dist": {
    "NOUN": 1
  },
  "sentences": {
    "featured": [
      {
        "text": "For the sake of your health, it is time to make regular exercise a part of your life.",
        "source": "2021_110_110學測英文試卷 ",
        "audio_file": "data/output/tts_audio/sentences/sake_ex_0_8a6fbc7b.mp3"
      }
    ],
    "other": []
  },
  "definition": {
    "zh_def": "日本的一種酒，通常由發酵的米製成。",
    "en_def": "A Japanese alcoholic beverage made from fermented rice.",
    "example": "She enjoyed a glass of sake with her sushi dinner."
  },
  "sentences_removed": 0
}