{
  "lemma": "sneeze",
  "count": 4,
  "pos_dist": {
    "VERB": 3,
    "NOUN": 1
  },
  "sentences": {
    "featured": [
      {
        "text": "This energy allowed the water 24 into the air, which looked just like sneezing!",
        "source": "2020_109_02-109學測英文試卷-定稿",
        "audio_file": "data/output/tts_audio/sentences/sneeze_ex_0_401d029e.mp3"
      },
      {
        "text": "They found that the sick plants could “sneeze” and 23 tiny water drops filled with leaf rust germs, spreading the disease to neighboring plants.",
        "source": "2020_109_02-109學測英文試卷-定稿",
        "audio_file": "data/output/tts_audio/sentences/sneeze_ex_1_1ce5f24b.mp3"
      },
      {
        "text": "However, not all plants can sneeze.",
        "source": "2020_109_02-109學測英文試卷-定稿",
        "audio_file": "data/output/tts_audio/sentences/sneeze_ex_2_957e07ba.mp3"
      },
      {
        "text": "Plant diseases can also spread through tiny water drops that jump off leaves— a plant’s version of a sneeze.",
        "source": "2020_109_02-109學測英文試卷-定稿",
        "audio_file": "data/output/tts_audio/sentences/sneeze_ex_3_76ff8b50.mp3"
      }
    ],
    "other": []
  },
  "definition": {
    "zh_def": "打噴嚏；因刺激而引起的突然呼吸道排氣。",
    "en_def": "To expel air from the nose and mouth suddenly and involuntarily, often as a reflex to irritation in the nasal passages.",
    "example": "She couldn't stop herself from sneezing when the pollen count was high."
  },
  "sentences_removed": 0
}