{
  "lemma": "unforgettable",
  "count": 1,
  "pos_dist": {
    "ADJ": 1
  },
  "sentences": {
    "featured": [
      {
        "text": "Wildlife encounters are unforgettable experiences for children and adults alike.",
        "source": "2025_114_02-114學測英文試題",
        "audio_file": "data/output/tts_audio/sentences/unforgettable_ex_0_d6c21054.mp3"
      }
    ],
    "other": []
  },
  "definition": {
    "zh_def": "難以忘懷的；令人難以忘記的",
    "en_def": "Something that is so remarkable or extraordinary that it cannot be forgotten.",
    "example": "The concert was an unforgettable experience for everyone who attended."
  },
  "sentences_removed": 0
}